praetor/__init__.py
praetor/add_quality.py
praetor/convert2prov.py
praetor/decorate.py
praetor/genBindings.py
praetor/get_import_versions.py
praetor/praetorTemplates.py
praetor/praetor_analysis_neo.py
praetor/praetor_analysis_rdf.py
praetor/praetor_settings.py
praetor/python_builtin_wrap_templateGen.py
praetor/python_modules.py
praetor/templateDictionary.py
praetor-3.8.1.data/scripts/add_quality.py
praetor-3.8.1.data/scripts/praetor_run.py
praetor-3.8.1.dist-info/LICENSE.txt
praetor-3.8.1.dist-info/METADATA
praetor-3.8.1.dist-info/WHEEL
praetor-3.8.1.dist-info/top_level.txt
praetor-3.8.1.dist-info/RECORD
