Metadata-Version: 2.1
Name: praetor
Version: 3.8.1
Summary: Automatic Generation of Provenance from Python3 Scripts
Home-page: https://gitlab.mpcdf.mpg.de/PRAETOR/prov-PRAETOR_public/
Author: Michael Johnson
Author-email: michael.johnson0100@gmail.com
License: MIT
Requires-Python: >=3.7
License-File: LICENSE.txt
Requires-Dist: codegen
Requires-Dist: matplotlib
Requires-Dist: memory-profiler
Requires-Dist: pymongo
Requires-Dist: rdflib
Requires-Dist: pandas
Requires-Dist: prov
Requires-Dist: requests
